tests/__init__.py
tests/test_qiniu_oss.py
tests/test_toutiao.py
tybase/__init__.py
tybase/datatest.txt
tybase/tytest.py
tybase/adtools/__init__.py
tybase/adtools/toutiaoBase.py
tybase/baidu/__init__.py
tybase/baidu/kw_tool.py
tybase/dbtool/__init__.py
tybase/dbtool/data_import.py
tybase/dbtool/mysql.py
tybase/google_tool/__init__.py
tybase/google_tool/drive.py
tybase/google_tool/processor.py
tybase/google_tool/slides.py
tybase/lc/__init__.py
tybase/lc/eg1.py
tybase/tools/Task.py
tybase/tools/__init__.py
tybase/tools/ali_oss_tools.py
tybase/tools/basetools.py
tybase/tools/down_tools.py
tybase/tools/image_compressor.py
tybase/tools/image_utils.py
tybase/tools/other_tool.py
tybase/tools/qiniu_oss_tools.py
tybase/tools/qiniu_tools.py
tybase/tools/riqit_ools.py
tybase/tools/riqit_tools.py
tybase/tools/video_utils.py
tybase/框架/__init__.py
tybase/框架/test.py
tybase/框架/运维分析框架.py
tybase-0.5.8.dist-info/METADATA
tybase-0.5.8.dist-info/WHEEL
tybase-0.5.8.dist-info/top_level.txt
tybase-0.5.8.dist-info/RECORD
