Metadata-Version: 2.1
Name: tybase
Version: 0.5.8
Summary: 修复视频合并
Home-page: https://github.com/yourusername/your_package
Author: Tuya
Author-email: 353335447@qq.com
Classifier: Development Status :: 3 - Alpha
Classifier: Intended Audience :: Developers
Classifier: License :: OSI Approved :: MIT License
Classifier: Programming Language :: Python :: 3.10
Requires-Dist: setuptools
Requires-Dist: opencv-python
Requires-Dist: Pillow
Requires-Dist: redis
Requires-Dist: celery
Requires-Dist: loguru
Requires-Dist: openpyxl
Requires-Dist: requests
Requires-Dist: python-dotenv
Requires-Dist: retrying
Requires-Dist: pymysql
Requires-Dist: mysql-connector-python
Requires-Dist: sqlalchemy
Requires-Dist: pandas
Requires-Dist: langchain
Requires-Dist: openai
Requires-Dist: oss2
Requires-Dist: google-auth
Requires-Dist: google-auth-oauthlib
Requires-Dist: google-auth-httplib2
Requires-Dist: google-api-python-client
